{
  "AWSTemplateFormatVersion": "2010-09-09",
  "Conditions": {
    "AssignInstanceRole": {
      "Fn::Not": [
        { "Fn::Equals": [ { "Ref": "InstanceRoleProfile" }, "" ] }
      ]
    },
    "AssignPublicIp": {
      "Fn::Not": [
        { "Fn::Equals": [ { "Ref": "NoPublicIp" }, "true" ] }
      ]
    },
    "AssignStaticPrivateIp": {
      "Fn::Not": [
        { "Fn::Equals": [ { "Ref": "PrivateIp" }, "" ] }
      ]
    },
    "AttachToElb": {
      "Fn::Not": [
        { "Fn::Equals": [ { "Ref": "ElbName" }, "" ] }
      ]
    },
    "CreateAppVolume": {
      "Fn::Equals": [ { "Ref": "AppVolumeDevice" }, "true" ]
    },
    "InstallCloudWatchAgent": {
      "Fn::Not": [
        { "Fn::Equals": [ { "Ref": "CloudWatchAgentUrl" }, "" ] }
      ]
    },
    "InstallUpdates": {
      "Fn::Not": [
        { "Fn::Equals": [ { "Ref": "NoUpdates" }, "true" ] }
      ]
    },
    "NotGenFive": {
      "Fn::Not": [
        {
          "Fn::Or": [
            {
              "Fn::Equals": [
                { "Fn::Select": [
                    "0",
                    { "Fn::Split": [ ".", { "Ref": "InstanceType" } ] }
                  ]
                },
                "c5"
              ]
            },
            {
              "Fn::Equals": [
                { "Fn::Select": [
                    "0",
                    { "Fn::Split": [ ".", { "Ref": "InstanceType" } ] }
                  ]
                },
                "m5"
              ]
            },
            {
              "Fn::Equals": [
                { "Fn::Select": [
                    "0",
                    { "Fn::Split": [ ".", { "Ref": "InstanceType" } ] }
                  ]
                },
                "t3"
              ]
            }
          ]
        }
      ]
    },
    "Reboot": {
      "Fn::Not": [
        { "Fn::Equals": [ { "Ref": "NoReboot" }, "true" ] }
      ]
    },
    "UseAdminGroups": {
      "Fn::Not": [
        { "Fn::Equals": [ { "Ref": "WatchmakerAdminGroups" }, "" ] }
      ]
    },
    "UseAdminPubkeyURL": {
      "Fn::Not": [
        { "Fn::Equals": [ { "Ref": "AdminPubkeyURL" }, "" ] }
      ]
    },
    "UseAdminUsers": {
      "Fn::Not": [
        { "Fn::Equals": [ { "Ref": "WatchmakerAdminUsers" }, "" ] }
      ]
    },
    "UseCfnAppInstaller": {
      "Fn::Not": [
        { "Fn::Equals": [ { "Ref": "GitLabConfScript" }, "" ] }
      ]
    },
    "UseCfnUrl": {
      "Fn::Not": [
        { "Fn::Equals": [ { "Ref": "CfnEndpointUrl" }, "" ] }
      ]
    },
    "UseComputerName": {
      "Fn::Not": [
        { "Fn::Equals": [ { "Ref": "WatchmakerComputerName" }, "" ] }
      ]
    },
    "UseEnvironment": {
      "Fn::Not": [
        { "Fn::Equals": [ { "Ref": "WatchmakerEnvironment" }, "" ] }
      ]
    },
    "UseKeyPair": {
      "Fn::Not": [
        { "Fn::Equals": [ { "Ref": "KeyPairName" }, "" ] }
      ]
    },
    "UseOsPrepScript": {
      "Fn::Not": [
        { "Fn::Equals": [ { "Ref": "GitLabPrepScript" }, "" ] }
      ]
    },
    "UseOuPath": {
      "Fn::Not": [
        { "Fn::Equals": [ { "Ref": "WatchmakerOuPath" }, "" ] }
      ]
    },
    "UseWamConfig": {
      "Fn::Not": [
        { "Fn::Equals": [ { "Ref": "WatchmakerConfig" }, "" ] }
      ]
    },
    "UseWatchmaker": {
      "Fn::Equals": [ { "Ref": "WatchmakerAvailable" }, "true" ]
    }
  },
  "Description": "This template deploys a STIG-hardened Enterprise Linux 7 instance to host the GitLab service.",
  "Mappings": {
    "InstanceTypeCapabilities": {
      "IsGenFive": {
        "ExternDeviceName": "/dev/xvdf",
        "InternDeviceName": "/dev/nvme1n1"
      },
      "PreGenFive": {
        "ExternDeviceName": "/dev/xvdf",
        "InternDeviceName": "/dev/xvdf"
      }
    }
  },
  "Metadata": {
    "AWS::CloudFormation::Interface": {
      "ParameterGroups": [
        {
          "Label": {
            "default": "EC2 Instance Configuration"
          },
          "Parameters": [
            "AmiId",
            "InstanceType",
            "RootVolumeSize",
            "ProvisionUser",
            "KeyPairName",
            "AdminPubkeyURL",
            "SecurityGroupIds",
            "InstanceRoleName",
            "InstanceRoleProfile",
            "SubnetId",
            "PrivateIp",
            "NoPublicIp",
            "NoReboot",
            "NoUpdates",
            "ToggleCfnInitUpdate"
          ]
        },
        {
          "Label": {
            "default": "Application Configuration"
          },
          "Parameters": [
            "GitLabRpmSourceUri",
            "GitLabRpmName",
            "GitLabConfScript",
            "GitLabPrepScript",
            "ConfigBucketPath",
            "AppVolumeDevice",
            "AppVolumeMountPath",
            "AppVolumeSize",
            "AppVolumeType",
            "GitRepoShareType",
            "GitRepoShareUri",
            "ElbName",
            "ProxyName",
            "BackupBucket",
            "BackupFolder"
          ]
        },
        {
          "Label": {
            "default": "Database Configuration"
          },
          "Parameters": [
            "RdsDbHost",
            "RdsDbInstance",
            "RdsDbAdmin",
            "RdsDbPasswd"
          ]
        },
        {
          "Label": {
            "default": "CloudFormation Configuration"
          },
          "Parameters": [
            "CfnEndpointUrl",
            "CfnGetPipUrl",
            "CfnBootstrapUtilsUrl",
            "CloudWatchAgentUrl"
          ]
        },
        {
          "Label": {
            "default": "EC2 Watchmaker Configuration"
          },
          "Parameters": [
            "PypiIndexUrl",
            "WatchmakerConfig",
            "WatchmakerEnvironment",
            "WatchmakerOuPath",
            "WatchmakerComputerName",
            "WatchmakerAdminGroups",
            "WatchmakerAdminUsers"
          ]
        }
      ],
      "ParameterLabels": {
        "ToggleCfnInitUpdate": {
          "default": "Force Cfn Init Update"
        }
      }
    },
    "Version": "1.5.6"
  },
  "Outputs": {
    "GitLabMasterId": {
      "Description": "Instance ID",
      "Value": { "Ref": "GitLabMaster" }
    },
    "GitLabMasterLogGroupName": {
      "Condition": "InstallCloudWatchAgent",
      "Description": "Log Group Name",
      "Value": { "Ref": "GitLabMasterLogGroup" }
    }
  },
  "Parameters": {
    "AdminPubkeyURL": {
      "AllowedPattern": "^$|^http://.*$|^https://.*$",
      "Description": "URL the file containing the admin users' SSH public keys.",
      "Type": "String"
    },
    "AmiId": {
      "Description": "ID of the AMI to launch",
      "Type": "AWS::EC2::Image::Id"
    },
    "AppVolumeDevice": {
      "AllowedValues": [
        "true",
        "false"
      ],
      "Default": "false",
      "Description": "Decision on whether to mount an extra EBS volume. Leave as default (\"false\") to launch without an extra application volume",
      "Type": "String"
    },
    "AppVolumeMountPath": {
      "AllowedPattern": "/.*",
      "Default": "/opt/data",
      "Description": "Filesystem path to mount the extra app volume. Ignored if \"AppVolumeDevice\" is false",
      "Type": "String"
    },
    "AppVolumeSize": {
      "ConstraintDescription": "Must be between 1GB and 16384GB.",
      "Default": "1",
      "Description": "Size in GB of the EBS volume to create. Ignored if \"AppVolumeDevice\" is false",
      "MaxValue": "16384",
      "MinValue": "1",
      "Type": "Number"
    },
    "AppVolumeType": {
      "AllowedValues": [
        "gp2",
        "io1",
        "sc1",
        "st1",
        "standard"
      ],
      "Default": "gp2",
      "Description": "Type of EBS volume to create. Ignored if \"AppVolumeDevice\" is false",
      "Type": "String"
    },
    "BackupBucket": {
      "AllowedPattern": "^[a-zA-Z][a-zA-Z0-9-]*[a-zA-Z0-9]*$|^$",
      "Description": "S3 Bucket to host backups of GitLab config- and app-data",
      "Type": "String"
    },
    "BackupFolder": {
      "AllowedPattern": "^[a-zA-Z][a-zA-Z0-9-]*[a-zA-Z0-9]*$|^$",
      "Description": "S3 Bucket to host backups of GitLab config- and app-data",
      "Type": "String"
    },
    "CfnBootstrapUtilsUrl": {
      "AllowedPattern": "^http[s]?://.*\\.tar\\.gz$",
      "Default": "https://s3.amazonaws.com/cloudformation-examples/aws-cfn-bootstrap-latest.tar.gz",
      "Description": "URL to aws-cfn-bootstrap-latest.tar.gz",
      "Type": "String"
    },
    "CfnEndpointUrl": {
      "AllowedPattern": "^$|^http[s]?://.*$",
      "Default": "https://cloudformation.us-east-1.amazonaws.com",
      "Description": "(Optional) URL to the CloudFormation Endpoint. e.g. https://cloudformation.us-east-1.amazonaws.com",
      "Type": "String"
    },
    "CfnGetPipUrl": {
      "AllowedPattern": "^http[s]?://.*\\.py$",
      "Default": "https://bootstrap.pypa.io/2.6/get-pip.py",
      "Description": "URL to get-pip.py",
      "Type": "String"
    },
    "CloudWatchAgentUrl": {
      "AllowedPattern": "^$|^s3://.*$",
      "Default": "",
      "Description": "(Optional) S3 URL to CloudWatch Agent installer. Example: s3://amazoncloudwatch-agent/linux/amd64/latest/AmazonCloudWatchAgent.zip",
      "Type": "String"
    },
    "ConfigBucketPath": {
      "Default": "",
      "Description": "S3 bucket-path to GitLab configuration template-file.",
      "Type": "String"
    },
    "ElbName": {
      "Default": "",
      "Description": "Logical name of the Classic ELB to attach this instance to.",
      "Type": "String"
    },
    "GitLabConfScript": {
      "AllowedPattern": "^$|^http[s]://.*\\.sh$",
      "Description": "URL of the script that localizes GitLab for running in the target environment",
      "Type": "String"
    },
    "GitLabPrepScript": {
      "AllowedPattern": "^$|^http[s]://.*\\.sh$",
      "Description": "URL of the script that preps the OS to host GitLab",
      "Type": "String"
    },
    "GitLabRpmName": {
      "AllowedPattern": "^gitlab-.*$",
      "Description": "Name of GitLab RPM to install. Include release version if 'other-than-latest' is desired. Example values would be: gitlab-ce, gitlab-ce-X.Y.Z",
      "Type": "String"
    },
    "GitLabRpmSourceUri": {
      "AllowedPattern": "^http://.*$|^https://.*$",
      "Default": "https://packages.gitlab.com/install/repositories/gitlab/gitlab-ce/config_file.repo?os=el&dist=7",
      "Description": "Url from which to download the Yum repository-definition for GitLab.",
      "Type": "String"
    },
    "GitRepoShareType": {
      "AllowedValues": [
        "glusterfs",
        "nfs"
      ],
      "Description": "Type of network share hosting persisted git repository content.",
      "Type": "String"
    },
    "GitRepoShareUri": {
      "Description": "URI of network share hosting persisted git repository content.",
      "Type": "String"
    },
    "InstanceRoleName": {
      "Default": "",
      "Description": "(Optional) IAM instance role to apply to the instance",
      "Type": "String"
    },
    "InstanceRoleProfile": {
      "Default": "",
      "Description": "(Optional) IAM instance-role profile to apply to the instance(s)",
      "Type": "String"
    },
    "InstanceType": {
      "AllowedValues": [
        "c4.large",
        "c4.xlarge",
        "c4.2xlarge",
        "c4.4xlarge",
        "c5.large",
        "c5.xlarge",
        "c5.2xlarge",
        "c5.4xlarge",
        "m4.large",
        "m4.xlarge",
        "m4.2xlarge",
        "m4.4xlarge",
        "m5.large",
        "m5.xlarge",
        "m5.2xlarge",
        "m5.4xlarge",
        "t2.medium",
        "t2.large",
        "t2.xlarge",
        "t2.2xlarge",
        "t3.medium",
        "t3.large",
        "t3.xlarge",
        "t3.2xlarge"
      ],
      "Default": "t2.large",
      "Description": "Amazon EC2 instance type",
      "Type": "String"
    },
    "KeyPairName": {
      "Description": "Public/private key pairs allow you to securely connect to your instance after it launches",
      "Type": "String"
    },
    "NoPublicIp": {
      "AllowedValues": [
        "false",
        "true"
      ],
      "Default": "true",
      "Description": "Controls whether to assign the instance a public IP. Recommended to leave at \"true\" _unless_ launching in a public subnet",
      "Type": "String"
    },
    "NoReboot": {
      "AllowedValues": [
        "false",
        "true"
      ],
      "Default": "false",
      "Description": "Controls whether to reboot the instance as the last step of cfn-init execution",
      "Type": "String"
    },
    "NoUpdates": {
      "AllowedValues": [
        "false",
        "true"
      ],
      "Default": "false",
      "Description": "Controls whether to run yum update during a stack update (on the initial instance launch, Watchmaker _always_ installs updates)",
      "Type": "String"
    },
    "PrivateIp": {
      "Default": "",
      "Description": "(Optional) Set a static, primary private IP. Leave blank to auto-select a free IP",
      "Type": "String"
    },
    "ProvisionUser": {
      "Description": "Default login user account name.",
      "Type": "String",
      "Default": "autogitlab",
      "AllowedPattern": "[a-z0-9]{6,12}+",
      "ConstraintDescription": "Alphanumeric string between 6 and 12 characters."
    },
    "ProxyName": {
      "Description": "FQDN of public-facing reverse-proxy.",
      "Type": "String",
      "AllowedPattern": "^[a-z][a-z0-9.-]*[a-z]$",
      "ConstraintDescription": "DNS FQDN of the user-facing proxy server"
    },
    "PypiIndexUrl": {
      "AllowedPattern": "^http[s]?://.*$",
      "Default": "https://pypi.org/simple",
      "Description": "URL to the PyPi Index",
      "Type": "String"
    },
    "RdsDbHost": {
      "Description": "RDS End-point Name (FQDN)",
      "Type": "String",
      "AllowedPattern": "^[a-zA-Z0-9.-]*$",
      "ConstraintDescription": "Alphanumeric string DNS FQDN representing the RDS end-point name."
    },
    "RdsDbInstance": {
      "Description": "RDS database name.",
      "Type": "String",
      "AllowedPattern": "^[a-z][a-zA-Z0-9_]*$",
      "ConstraintDescription": "Alphanumeric string representing the RDS database instance."
    },
    "RdsDbAdmin": {
      "Description": "RDS database-user name.",
      "Type": "String",
      "AllowedPattern": "^[a-z][a-z0-9]*$",
      "ConstraintDescription": "Alphanumeric string representing the RDS database-user name."
    },
    "RdsDbPasswd": {
      "Description": "RDS database-user login password.",
      "NoEcho": "True",
      "Type": "String"
    },
    "RootVolumeSize": {
      "ConstraintDescription": "Must be between 20GB and 16384GB.",
      "Default": "20",
      "Description": "Size in GB of the EBS volume to create. If smaller than AMI default, create operation will fail; If larger, root device-volume's partition size will be increased",
      "MaxValue": "16384",
      "MinValue": "20",
      "Type": "Number"
    },
    "SecurityGroupIds": {
      "Description": "List of security groups to apply to the instance",
      "Type": "List<AWS::EC2::SecurityGroup::Id>"
    },
    "SubnetId": {
      "Description": "ID of the subnet to assign to the instance",
      "Type": "AWS::EC2::Subnet::Id"
    },
    "ToggleCfnInitUpdate": {
      "AllowedValues": [
        "A",
        "B"
      ],
      "Default": "A",
      "Description": "A/B toggle that forces a change to instance metadata, triggering the cfn-init update sequence",
      "Type": "String"
    },
    "WatchmakerAdminGroups": {
      "Default": "",
      "Description": "(Optional) Colon-separated list of domain groups that should have admin permissions on the EC2 instance",
      "Type": "String"
    },
    "WatchmakerAdminUsers": {
      "Default": "",
      "Description": "(Optional) Colon-separated list of domain users that should have admin permissions on the EC2 instance",
      "Type": "String"
    },
    "WatchmakerAvailable": {
      "AllowedValues": [
        "false",
        "true"
      ],
      "Default": "true",
      "Description": "Specify if Watchmaker is available (if \"false\" all other Watchmaker-related parms will be ignored).",
      "Type": "String"
    },
    "WatchmakerComputerName": {
      "Default": "",
      "Description": "(Optional) Sets the hostname/computername within the OS",
      "Type": "String"
    },
    "WatchmakerConfig": {
      "AllowedPattern": "^$|^(http[s]?|s3|file)://.*$",
      "Default": "",
      "Description": "(Optional) Path to a Watchmaker config file.  The config file path can be a remote source (i.e. http[s]://, s3://) or local directory (i.e. file://)",
      "Type": "String"
    },
    "WatchmakerEnvironment": {
      "AllowedValues": [
        "",
        "dev",
        "test",
        "prod"
      ],
      "Default": "",
      "Description": "Environment in which the instance is being deployed",
      "Type": "String"
    },
    "WatchmakerOuPath": {
      "AllowedPattern": "^$|^(OU=.+,)+(DC=.+)+$",
      "Default": "",
      "Description": "(Optional) DN of the OU to place the instance when joining a domain. If blank and \"WatchmakerEnvironment\" enforces a domain join, the instance will be placed in a default container. Leave blank if not joining a domain, or if \"WatchmakerEnvironment\" is \"false\"",
      "Type": "String"
    }
  },
  "Resources": {
    "GitLabMaster": {
      "CreationPolicy": {
        "ResourceSignal": {
          "Count": "1",
          "Timeout": "PT30M"
        }
      },
      "Metadata": {
        "AWS::CloudFormation::Init": {
          "admkey-install": {
            "commands": {
              "1-install-keyfile": {
                "command": "bash -xe /etc/cfn/scripts/admkey.sh"
              }
            },
            "files": {
              "/etc/cfn/files/AdminKeys.pub": {
                "group": "root",
                "mode": "000600",
                "owner": "root",
                "source": { "Ref": "AdminPubkeyURL" }
              },
              "/etc/cfn/scripts/admkey.sh": {
                "content": {
                  "Fn::Join": [
                    "",
                    [
                      "#!/bin/bash\n\n",
                      "PROVHOME=$(getent passwd ",
                      { "Ref": "ProvisionUser" },
                      " | awk -F\":\" '{print $6}')\n",
                      "\n",
                      "install -b -m 000600 -o ",
                      { "Ref": "ProvisionUser" },
                      " -g ",
                      { "Ref": "ProvisionUser" },
                      " /etc/cfn/files/AdminKeys.pub ${PROVHOME}/.ssh/authorized_keys\n",
                      "\n"
                    ]
                  ]
                },
                "group": "root",
                "mode": "000700",
                "owner": "root"
              }
            }
          },
          "app-prep": {
            "commands": {
              "10-config_svc-reload": {
                "command": "systemctl daemon-reload"
              },
              "20-config_svc-reload": {
                "command": "systemctl enable gitlab-config.service"
              }
            },
            "files": {
              "/etc/cfn/scripts/glprep.sh": {
                "source": { "Ref": "GitLabConfScript" },
                "group": "root",
                "mode": "000700",
                "owner": "root"
              },
              "/etc/systemd/system/gitlab-config.service": {
                "content": {
                  "Fn::Join": [
                    "",
                    [
                      "[Unit]\n",
                      "Description=Reconfigure GitLab to work on this host\n",
                      "After=multi-user.target\n",
                      "\n",
                      "[Service]\n",
                      "Type=oneshot\n",
                      "ExecStart=/etc/cfn/scripts/glprep.sh\n",
                      "\n",
                      "[Install]\n",
                      "WantedBy=multi-user.target\n"
                    ]
                  ]
                },
                "group": "root",
                "mode": "000644",
                "owner": "root"
              },
              "/etc/cfn/scripts/glprep-signal.sh": {
                "content": {
                  "Fn::Join": [
                    "",
                    [
                      "#!/bin/bash\n",
                      "#\n",
                      "# Small script to send a post-reboot CFn signal\n",
                      "#\n",
                      "###################################################\n",
                      "PATH=${PATH}:/opt/aws/bin\n",
                      "\n",
                      "logger -p kern.info -t ${0} -s \"Sending signal '${1}' to CFn...\"\n",
                      "\n",
                      "cfn-signal -e ${1} --stack ",
                      { "Ref": "AWS::StackName" },
                      " --resource GitLabMaster",
                      {
                        "Fn::If": [
                          "AssignInstanceRole",
                          {
                            "Fn::Join": [
                              "",
                              [
                                " --role ",
                                { "Ref": "InstanceRoleName" }
                              ]
                            ]
                          },
                          ""
                        ]
                      },
                      {
                        "Fn::If": [
                          "UseCfnUrl",
                          {
                            "Fn::Join": [
                              "",
                              [
                                " --url ",
                                { "Ref": "CfnEndpointUrl" }
                              ]
                            ]
                          },
                          ""
                        ]
                      },
                      " --region ",
                      { "Ref": "AWS::Region" },
                      "\n"
                    ]
                  ]
                },
                "group": "root",
                "mode": "000755",
                "owner": "root"
              },
              "/etc/cron.d/GitLabBackup": {
                "content": {
                  "Fn::Join": [
                    "",
                    [
                      "SHELL=/bin/bash\n",
                      "PATH=/sbin:/bin:/usr/sbin:/usr/bin\n",
                      "MAILTO=\"\"\n",
                      "\n",
                      "0 23 * * * root /usr/local/bin/gitlab-backup.cron\n"
                    ]
                  ]
                },
                "group": "root",
                "mode": "000644",
                "owner": "root"
              },
              "/usr/local/bin/gitlab-backup.cron": {
                "content": {
                  "Fn::Join": [
                    "",
                    [
                      "#!/bin/bash\n",
                      "#\n",
                      "# Script to backup GitLab data to S3 bucket\n",
                      "#################################################################\n",
                      "PROGNAME=$(basename \"${0}\")\n",
                      "LOGFACIL=\"user.err\"\n",
                      "for VAR in $(cat /etc/cfn/GitLab.envs)\n",
                      "do\n",
                      "   export $VAR\n",
                      "done\n",
                      "BUCKET=\"${GITLAB_BACKUP_BUCKET:-UNDEF}\"\n",
                      "FOLDER=\"${GITLAB_BACKUP_FOLDER:-UNDEF}\"\n",
                      "REGION=\"${GITLAB_AWS_REGION:-UNDEF}\"\n",
                      "DAYSUB=\"$(date '+%A')\"\n",
                      "SRCDIR=/var/opt/gitlab/backups/\n",
                      "            \n",
                      "# Set up flexible logging\n",
                      "function err_exit {\n",
                      "   echo \"${1}\"\n",
                      "   logger -t \"${PROGNAME}\" -p ${LOGFACIL} \"${1}\"\n",
                      "   exit 1\n",
                      "}\n",
                      "\n",
                      "# Create GitLab archive file\n",
                      "printf \"Creating backup archive-file in s3://%s...\" \"${BUCKET}\"\n",
                      "gitlab-rake gitlab:backup:create STRATEGY=copy DIRECTORY=\"${FOLDER}\" ",
                        "CRON=1 &&  echo \"Success\" || ",
                        "err_exit 'Failed creating backup archive-file'\n"
                    ]
                  ]
                },
                "group": "root",
                "mode": "000700",
                "owner": "root"
              }
            }
          },
          "configSets": {
            "launch": [
              "setup",
              {
                "Fn::If": [
                  "UseAdminPubkeyURL",
                  "admkey-install",
                  { "Ref": "AWS::NoValue" }
                ]
              },
              {
                "Fn::If": [
                  "InstallCloudWatchAgent",
                  "cw-agent-install",
                  { "Ref": "AWS::NoValue" }
                ]
              },
              {
                "Fn::If": [
                  "UseWatchmaker",
                  [
                    "watchmaker-install",
                    "watchmaker-launch",
                    "watchmaker-defips"
                  ],
                  { "Ref": "AWS::NoValue" }
                ]
              },
              {
                "Fn::If": [
                  "UseOsPrepScript",
                  "osprep",
                  { "Ref" : "AWS::NoValue" }
                ]
              },
              {
                "Fn::If": [
                  "UseCfnAppInstaller",
                  [
                    "gitlab-tmplt-fetch",
                    "app-prep"
                  ],
                  { "Ref" : "AWS::NoValue" }
                ]
              },
              {
                "Fn::If": [
                  "Reboot",
                  "reboot",
                  { "Ref": "AWS::NoValue" }
                ]
              }
            ],
            "update": [
              "setup",
              {
                "Fn::If": [
                  "UseAdminPubkeyURL",
                  "admkey-install",
                  { "Ref": "AWS::NoValue" }
                ]
              },
              {
                "Fn::If": [
                  "InstallUpdates",
                  "install-updates",
                  { "Ref": "AWS::NoValue" }
                ]
              },
              {
                "Fn::If": [
                  "UseWatchmaker",
                  [
                    "watchmaker-install",
                    "watchmaker-launch",
                    "watchmaker-defips"
                  ],
                  { "Ref": "AWS::NoValue" }
                ]
              },
              {
                "Fn::If": [
                  "UseOsPrepScript",
                  "osprep",
                  { "Ref" : "AWS::NoValue" }
                ]
              },
              {
                "Fn::If": [
                  "UseCfnAppInstaller",
                  [
                    "gitlab-tmplt-fetch",
                    "app-prep"
                  ],
                  { "Ref" : "AWS::NoValue" }
                ]
              },
              {
                "Fn::If": [
                  "Reboot",
                  "reboot",
                  { "Ref": "AWS::NoValue" }
                ]
              }
            ]
          },
          "cw-agent-install": {
            "commands": {
              "01-get-cloudwatch-agent": {
                "command": {
                  "Fn::Join": [
                    "",
                    [
                      "install -Dbm 700 -o root -g root /dev/null /etc/cfn/scripts/AmazonCloudWatchAgent.zip &&",
                      " aws s3 cp ",
                      { "Ref": "CloudWatchAgentUrl" },
                      " /etc/cfn/scripts/AmazonCloudWatchAgent.zip"
                    ]
                  ]
                }
              },
              "02-extract-cloudwatch-agent": {
                "command": {
                  "Fn::Join": [
                    "",
                    [
                      "yum -y install unzip &&",
                      "unzip /etc/cfn/scripts/AmazonCloudWatchAgent.zip -d /etc/cfn/scripts/aws-cw-agent"
                    ]
                  ]
                }
              },
              "10-install-cloudwatch-agent": {
                "command": {
                  "Fn::Join": [
                    "",
                    [
                      " bash -xe install.sh &&",
                      " /opt/aws/amazon-cloudwatch-agent/bin/amazon-cloudwatch-agent-ctl",
                      " -a fetch-config -m ec2 -c",
                      " file:/opt/aws/amazon-cloudwatch-agent/etc/amazon-cloudwatch-agent.json -s"
                    ]
                  ]
                },
                "cwd": "/etc/cfn/scripts/aws-cw-agent"
              }
            },
            "files": {
              "/opt/aws/amazon-cloudwatch-agent/etc/amazon-cloudwatch-agent.json": {
                "content": {
                  "Fn::Join": [
                    "",
                    [
                      "{",
                      "  \"logs\": {\n",
                      "  \"logs_collected\": {\n",
                      "  \"files\": {\n",
                      "  \"collect_list\": [\n",
                      "  {\n",
                      "  \"file_path\": \"/opt/aws/amazon-cloudwatch-agent/logs/amazon-cloudwatch-agent.log\",\n",
                      "  \"log_group_name\": \"",
                      {
                        "Fn::If": [
                          "InstallCloudWatchAgent",
                          { "Ref": "GitLabMasterLogGroup" },
                          { "Ref": "AWS::NoValue" }
                        ]
                      },
                      "\",\n",
                      "  \"log_stream_name\": \"cloudwatch_agent_logs_{instance_id}\",\n",
                      "  \"timestamp_format\": \"%H:%M:%S %y %b %-d\"\n",
                      "  },\n",
                      "  {\n",
                      "  \"file_path\": \"/var/log/cfn-init.log\",\n",
                      "  \"log_group_name\": \"",
                      {
                        "Fn::If": [
                          "InstallCloudWatchAgent",
                          { "Ref": "GitLabMasterLogGroup" },
                          { "Ref": "AWS::NoValue" }
                        ]
                      },
                      "\",\n",
                      "  \"log_stream_name\": \"cfn_init_logs_{instance_id}\",\n",
                      "  \"timestamp_format\": \"%H:%M:%S %y %b %-d\"\n",
                      "  },\n",
                      "  {\n",
                      "  \"file_path\": \"/var/log/messages\",\n",
                      "  \"log_group_name\": \"",
                      {
                        "Fn::If": [
                          "InstallCloudWatchAgent",
                          { "Ref": "GitLabMasterLogGroup" },
                          { "Ref": "AWS::NoValue" }
                        ]
                      },
                      "\",\n",
                      "  \"log_stream_name\": \"messages_logs_{instance_id}\",\n",
                      "  \"timestamp_format\": \"%H:%M:%S %y %b %-d\"\n",
                      "  },\n",
                      "  {\n",
                      "  \"file_path\": \"/var/log/watchmaker/watchmaker.log\",\n",
                      "  \"log_group_name\": \"",
                      {
                        "Fn::If": [
                          "InstallCloudWatchAgent",
                          { "Ref": "GitLabMasterLogGroup" },
                          { "Ref": "AWS::NoValue" }
                        ]
                      },
                      "\",\n",
                      "  \"log_stream_name\": \"watchmaker_logs_{instance_id}\",\n",
                      "  \"timestamp_format\": \"%H:%M:%S %y %b %-d\"\n",
                      "  },\n",
                      "  {\n",
                      "  \"file_path\": \"/var/log/watchmaker/salt_call.debug.log\",\n",
                      "  \"log_group_name\": \"",
                      {
                        "Fn::If": [
                          "InstallCloudWatchAgent",
                          { "Ref": "GitLabMasterLogGroup" },
                          { "Ref": "AWS::NoValue" }
                        ]
                      },
                      "\",\n",
                      "  \"log_stream_name\": \"salt_call_debug_logs_{instance_id}\",\n",
                      "  \"timestamp_format\": \"%H:%M:%S %y %b %-d\"\n",
                      "  },\n",
                      "      {\n",
                      "          \"file_path\": \"/var/log/gitlab/nginx/error.log\",\n",
                      "          \"log_group_name\": \"",
                      {
                        "Fn::If": [
                          "InstallCloudWatchAgent",
                          { "Ref": "GitLabMasterLogGroup" },
                          { "Ref": "AWS::NoValue" }
                        ]
                      },
                      "\",\n",
                      "          \"log_stream_name\": \"nginx_err_logs_{instance_id}\",\n",
                      "          \"timestamp_format\": \"%H:%M:%S %y %b %-d\"\n",
                      "      },\n",
                      "      {\n",
                      "          \"file_path\": \"/var/log/gitlab/nginx/access.log\",\n",
                      "          \"log_group_name\": \"",
                      {
                        "Fn::If": [
                          "InstallCloudWatchAgent",
                          { "Ref": "GitLabMasterLogGroup" },
                          { "Ref": "AWS::NoValue" }
                        ]
                      },
                      "\",\n",
                      "          \"log_stream_name\": \"nginx_access_logs_{instance_id}\",\n",
                      "          \"timestamp_format\": \"%H:%M:%S %y %b %-d\"\n",
                      "      },\n",
                      "      {\n",
                      "          \"file_path\": \"/var/log/gitlab/nginx/gitlab_error.log\",\n",
                      "          \"log_group_name\": \"",
                      {
                        "Fn::If": [
                          "InstallCloudWatchAgent",
                          { "Ref": "GitLabMasterLogGroup" },
                          { "Ref": "AWS::NoValue" }
                        ]
                      },
                      "\",\n",
                      "          \"log_stream_name\": \"nginx_gitlab_err_logs_{instance_id}\",\n",
                      "          \"timestamp_format\": \"%H:%M:%S %y %b %-d\"\n",
                      "      },\n",
                      "      {\n",
                      "          \"file_path\": \"/var/log/gitlab/nginx/gitlab_access.log\",\n",
                      "          \"log_group_name\": \"",
                      {
                        "Fn::If": [
                          "InstallCloudWatchAgent",
                          { "Ref": "GitLabMasterLogGroup" },
                          { "Ref": "AWS::NoValue" }
                        ]
                      },
                      "\",\n",
                      "          \"log_stream_name\": \"nginx_gitlab_access_logs_{instance_id}\",\n",
                      "          \"timestamp_format\": \"%H:%M:%S %y %b %-d\"\n",
                      "      },\n",
                      "      {\n",
                      "          \"file_path\": \"/var/log/gitlab/gitlab-rails/grpc.log\",\n",
                      "          \"log_group_name\": \"",
                      {
                        "Fn::If": [
                          "InstallCloudWatchAgent",
                          { "Ref": "GitLabMasterLogGroup" },
                          { "Ref": "AWS::NoValue" }
                        ]
                      },
                      "\",\n",
                      "          \"log_stream_name\": \"gitlab_grpc_logs_{instance_id}\",\n",
                      "          \"timestamp_format\": \"%H:%M:%S %y %b %-d\"\n",
                      "      },\n",
                      "      {\n",
                      "          \"file_path\": \"/var/log/gitlab/gitlab-rails/production.log\",\n",
                      "          \"log_group_name\": \"",
                      {
                        "Fn::If": [
                          "InstallCloudWatchAgent",
                          { "Ref": "GitLabMasterLogGroup" },
                          { "Ref": "AWS::NoValue" }
                        ]
                      },
                      "\",\n",
                      "          \"log_stream_name\": \"gitlab_production_logs_{instance_id}\",\n",
                      "          \"timestamp_format\": \"%H:%M:%S %y %b %-d\"\n",
                      "      },\n",
                      "      {\n",
                      "          \"file_path\": \"/var/log/gitlab/gitlab-rails/application.log\",\n",
                      "          \"log_group_name\": \"",
                      {
                        "Fn::If": [
                          "InstallCloudWatchAgent",
                          { "Ref": "GitLabMasterLogGroup" },
                          { "Ref": "AWS::NoValue" }
                        ]
                      },
                      "\",\n",
                      "          \"log_stream_name\": \"gitlab_application_logs_{instance_id}\",\n",
                      "          \"timestamp_format\": \"%H:%M:%S %y %b %-d\"\n",
                      "      },\n",
                      "      {\n",
                      "          \"file_path\": \"/var/log/gitlab/gitlab-rails/sidekiq.log\",\n",
                      "          \"log_group_name\": \"",
                      {
                        "Fn::If": [
                          "InstallCloudWatchAgent",
                          { "Ref": "GitLabMasterLogGroup" },
                          { "Ref": "AWS::NoValue" }
                        ]
                      },
                      "\",\n",
                      "          \"log_stream_name\": \"gitlab_sidekiq_logs_{instance_id}\",\n",
                      "          \"timestamp_format\": \"%H:%M:%S %y %b %-d\"\n",
                      "      }\n",
                      "  ]\n",
                      "  }\n",
                      "  },\n",
                      "  \"log_stream_name\": \"default_logs_{instance_id}\"\n",
                      "  }\n",
                      "}\n"
                    ]
                  ]
                }
              }
            }
          },
          "finalize": {
            "commands": {
              "10-signal-success": {
                "command": {
                  "Fn::Join": [
                    "",
                    [
                      "cfn-signal -e 0",
                      " --stack ",
                      { "Ref": "AWS::StackName" },
                      " --resource GitLabMaster",
                      {
                        "Fn::If": [
                          "AssignInstanceRole",
                          {
                            "Fn::Join": [
                              "",
                              [
                                " --role ",
                                { "Ref": "InstanceRoleName" }
                              ]
                            ]
                          },
                          ""
                        ]
                      },
                      {
                        "Fn::If": [
                          "UseCfnUrl",
                          {
                            "Fn::Join": [
                              "",
                              [
                                " --url ",
                                { "Ref": "CfnEndpointUrl" }
                              ]
                            ]
                          },
                          ""
                        ]
                      },
                      " --region ",
                      { "Ref": "AWS::Region" },
                      "\n"
                    ]
                  ]
                },
                "ignoreErrors": "true"
              }
            }
          },
          "gitlab-tmplt-fetch": {
            "commands": {
              "template-fetch": {
                "command": {
                  "Fn::Join": [
                    "",
                    [
                      "aws s3 cp s3://",
                      { "Ref": "ConfigBucketPath" },
                      " /etc/cfn/gitlab.rb.tmplt"
                    ]
                  ]
                }
              }
            }
          },
          "install-updates": {
            "commands": {
              "10-install-updates": {
                "command": "yum -y update"
              }
            }
          },
          "osprep": {
            "commands": {
              "10-osprep-launch": {
                "command": "bash -xe /etc/cfn/scripts/osprep.sh"
              }
            },
            "files": {
              "/etc/cfn/scripts/osprep.sh": {
                "source": { "Ref": "GitLabPrepScript" },
                "group": "root",
                "mode": "000700",
                "owner": "root"
              }
            }
          },
          "reboot": {
            "commands": {
              "10-reboot": {
                "command": "shutdown -r +1 &"
              }
            }
          },
          "setup": {
            "files": {
              "/etc/cfn/GitLab.envs": {
                "content": {
                  "Fn::Join": [
                    "",
                    [
                      "GITLAB_AWS_REGION=",
                        { "Ref": "AWS::Region" },
                        "\n",
                      "GITLAB_BACKUP_BUCKET=",
                        { "Ref": "BackupBucket" },
                        "\n",
                      "GITLAB_BACKUP_FOLDER=",
                        { "Ref": "BackupFolder" },
                        "\n",
                      "GITLAB_DATABASE=",
                        { "Ref": "RdsDbInstance" },
                        "\n",
                      "GITLAB_DBHOST=",
                        { "Ref": "RdsDbHost" },
                        "\n",
                      "GITLAB_DBUSER=",
                        { "Ref": "RdsDbAdmin" },
                        "\n",
                      "GITLAB_EXTERNURL=",
                        { "Ref": "ProxyName" },
                        "\n",
                      "GITLAB_PASSWORD=",
                        { "Ref": "RdsDbPasswd" },
                        "\n",
                      "GITLAB_PROXY_FQDN=",
                        { "Ref": "ProxyName" },
                        "\n",
                      "GITLAB_RPM_NAME=",
                        { "Ref": "GitLabRpmName" },
                        "\n",
                      "GITLAB_SHARE_TYPE=",
                        { "Ref": "GitRepoShareType" },
                        "\n",
                      "GITLAB_SHARE_URI=",
                        { "Ref": "GitRepoShareUri" },
                        "\n",
                      "GITLAB_YUM_CONFIG=",
                        { "Ref": "GitLabRpmSourceUri" },
                        "\n"
                    ]
                  ]
                },
                "group": "root",
                "mode": "000400",
                "owner": "root"
              },
              "/etc/cfn/cfn-hup.conf": {
                "content": {
                  "Fn::Join": [
                    "",
                    [
                      "[main]\n",
                      "stack=",
                      { "Ref": "AWS::StackId" },
                      "\n",
                      "region=",
                      { "Ref": "AWS::Region" },
                      "\n",
                      {
                        "Fn::If": [
                          "AssignInstanceRole",
                          {
                            "Fn::Join": [
                              "",
                              [
                                "role=",
                                { "Ref": "InstanceRoleName" },
                                "\n"
                              ]
                            ]
                          },
                          ""
                        ]
                      },
                      {
                        "Fn::If": [
                          "UseCfnUrl",
                          {
                            "Fn::Join": [
                              "",
                              [
                                "url=",
                                { "Ref": "CfnEndpointUrl" },
                                "\n"
                              ]
                            ]
                          },
                          ""
                        ]
                      },
                      "interval=1",
                      "\n",
                      "verbose=true",
                      "\n"
                    ]
                  ]
                },
                "group": "root",
                "mode": "000400",
                "owner": "root"
              },
              "/etc/cfn/hooks.d/cfn-auto-reloader.conf": {
                "content": {
                  "Fn::Join": [
                    "",
                    [
                      "[cfn-auto-reloader-hook]\n",
                      "triggers=post.update\n",
                      "path=Resources.GitLabMaster.Metadata\n",
                      "action=cfn-init -v -c update",
                      " --stack ",
                      { "Ref": "AWS::StackName" },
                      " --resource GitLabMaster",
                      { "Fn::If": [ "AssignInstanceRole",
                          {
                            "Fn::Join": [
                              "",
                              [
                                " --role ",
                                { "Ref": "InstanceRoleName" }
                              ]
                            ]
                          },
                          ""
                        ]
                      },
                      {
                        "Fn::If": [
                          "UseCfnUrl",
                          {
                            "Fn::Join": [
                              "",
                              [
                                " --url ",
                                { "Ref": "CfnEndpointUrl" }
                              ]
                            ]
                          },
                          ""
                        ]
                      },
                      " --region ",
                      { "Ref": "AWS::Region" },
                      "\n",
                      "runas=root\n"
                    ]
                  ]
                },
                "group": "root",
                "mode": "000400",
                "owner": "root"
              },
              "/etc/cfn/scripts/watchmaker-install.sh": {
                "content": {
                  "Fn::Join": [
                    "",
                    [
                      "#!/bin/bash\n\n",
                      "PYPI_URL=",
                      { "Ref": "PypiIndexUrl" },
                      "\n",
                      "curl --silent --show-error --retry 5 -L ",
                      { "Ref": "CfnGetPipUrl" },
                      " | python - --index-url=\"$PYPI_URL\" 'wheel<0.30.0;python_version<\"2.7\"' 'wheel;python_version>=\"2.7\"'",
                      "\n",
                      "pip install",
                      " --index-url=\"$PYPI_URL\"",
                      " --upgrade 'pip<10' 'setuptools<37;python_version<\"2.7\"' 'setuptools;python_version>=\"2.7\"' boto3\n",
                      "pip install",
                      " --index-url=\"$PYPI_URL\"",
                      " --upgrade watchmaker\n\n"
                    ]
                  ]
                },
                "group": "root",
                "mode": "000700",
                "owner": "root"
              }
            },
            "services": {
              "sysvinit": {
                "cfn-hup": {
                  "enabled": "true",
                  "ensureRunning": "true",
                  "files": [
                    "/etc/cfn/cfn-hup.conf",
                    "/etc/cfn/hooks.d/cfn-auto-reloader.conf"
                  ]
                }
              }
            }
          },
          "watchmaker-defips": {
            "commands": {
              "20-watchmaker-defips": {
                "command": "/bin/salt-call --local ash.fips_disable"
              }
            }
          },
          "watchmaker-install": {
            "commands": {
              "10-watchmaker-install": {
                "command": "bash -xe /etc/cfn/scripts/watchmaker-install.sh"
              }
            }
          },
          "watchmaker-launch": {
            "commands": {
              "10-watchmaker-launch": {
                "command": {
                  "Fn::Join": [
                    "",
                    [
                      "watchmaker --log-level debug",
                      " --log-dir /var/log/watchmaker",
                      " --no-reboot",
                      {
                        "Fn::If": [
                          "UseWamConfig",
                          {
                            "Fn::Join": [
                              "",
                              [
                                " --config \"",
                                { "Ref": "WatchmakerConfig" },
                                "\""
                              ]
                            ]
                          },
                          ""
                        ]
                      },
                      {
                        "Fn::If": [
                          "UseEnvironment",
                          {
                            "Fn::Join": [
                              "",
                              [
                                " --env \"",
                                { "Ref": "WatchmakerEnvironment" },
                                "\""
                              ]
                            ]
                          },
                          ""
                        ]
                      },
                      {
                        "Fn::If": [
                          "UseOuPath",
                          {
                            "Fn::Join": [
                              "",
                              [
                                " --ou-path \"",
                                { "Ref": "WatchmakerOuPath" },
                                "\""
                              ]
                            ]
                          },
                          ""
                        ]
                      },
                      {
                        "Fn::If": [
                          "UseComputerName",
                          {
                            "Fn::Join": [
                              "",
                              [
                                " --computer-name \"",
                                { "Ref": "WatchmakerComputerName" },
                                "\""
                              ]
                            ]
                          },
                          ""
                        ]
                      },
                      {
                        "Fn::If": [
                          "UseAdminGroups",
                          {
                            "Fn::Join": [
                              "",
                              [
                                " --admin-groups \"",
                                { "Ref": "WatchmakerAdminGroups" },
                                "\""
                              ]
                            ]
                          },
                          ""
                        ]
                      },
                      {
                        "Fn::If": [
                          "UseAdminUsers",
                          {
                            "Fn::Join": [
                              "",
                              [
                                " --admin-users \"",
                                { "Ref": "WatchmakerAdminUsers" },
                                "\""
                              ]
                            ]
                          },
                          ""
                        ]
                      }
                    ]
                  ]
                }
              }
            }
          },
          "watchmaker-update": {
            "commands": {
              "10-watchmaker-update": {
                "command": {
                  "Fn::Join": [
                    "",
                    [
                      "watchmaker --log-level debug",
                      " --log-dir /var/log/watchmaker",
                      " --salt-states None",
                      " --no-reboot",
                      {
                        "Fn::If": [
                          "UseWamConfig",
                          {
                            "Fn::Join": [
                              "",
                              [
                                " --config \"",
                                { "Ref": "WatchmakerConfig" },
                                "\""
                              ]
                            ]
                          },
                          ""
                        ]
                      },
                      {
                        "Fn::If": [
                          "UseEnvironment",
                          {
                            "Fn::Join": [
                              "",
                              [
                                " --env \"",
                                { "Ref": "WatchmakerEnvironment" },
                                "\""
                              ]
                            ]
                          },
                          ""
                        ]
                      },
                      {
                        "Fn::If": [
                          "UseOuPath",
                          {
                            "Fn::Join": [
                              "",
                              [
                                " --oupath \"",
                                { "Ref": "WatchmakerOuPath" },
                                "\""
                              ]
                            ]
                          },
                          ""
                        ]
                      },
                      {
                        "Fn::If": [
                          "UseComputerName",
                          {
                            "Fn::Join": [
                              "",
                              [
                                " --computer-name \"",
                                { "Ref": "WatchmakerComputerName" },
                                "\""
                              ]
                            ]
                          },
                          ""
                        ]
                      },
                      {
                        "Fn::If": [
                          "UseAdminGroups",
                          {
                            "Fn::Join": [
                              "",
                              [
                                " --admin-groups \"",
                                { "Ref": "WatchmakerAdminGroups" },
                                "\""
                              ]
                            ]
                          },
                          ""
                        ]
                      },
                      {
                        "Fn::If": [
                          "UseAdminUsers",
                          {
                            "Fn::Join": [
                              "",
                              [
                                " --admin-users \"",
                                { "Ref": "WatchmakerAdminUsers" },
                                "\""
                              ]
                            ]
                          },
                          ""
                        ]
                      }
                    ]
                  ]
                }
              }
            }
          }
        },
        "ToggleCfnInitUpdate": { "Ref": "ToggleCfnInitUpdate" }
      },
      "Properties": {
        "BlockDeviceMappings": [
          {
            "DeviceName": "/dev/sda1",
            "Ebs": {
              "DeleteOnTermination": true,
              "VolumeSize": { "Ref": "RootVolumeSize" },
              "VolumeType": "gp2"
            }
          },
          {
            "Fn::If": [
              "CreateAppVolume",
              {
                "DeviceName": "/dev/xvdf",
                "Ebs": {
                  "DeleteOnTermination": true,
                  "VolumeSize": { "Ref": "AppVolumeSize" },
                  "VolumeType": { "Ref": "AppVolumeType" }
                }
              },
              { "Ref": "AWS::NoValue" }
            ]
          }
        ],
        "IamInstanceProfile": {
          "Fn::If": [
            "AssignInstanceRole",
            { "Ref": "InstanceRoleProfile" },
            { "Ref": "AWS::NoValue" }
          ]
        },
        "ImageId": { "Ref": "AmiId" },
        "InstanceType": { "Ref": "InstanceType" },
        "KeyName": {
          "Fn::If": [
            "UseKeyPair",
            { "Ref": "KeyPairName" },
            { "Ref": "AWS::NoValue" }
          ]
        },
        "NetworkInterfaces": [
          {
            "AssociatePublicIpAddress": {
              "Fn::If": [
                "AssignPublicIp",
                true,
                false
              ]
            },
            "DeviceIndex": "0",
            "GroupSet": { "Ref": "SecurityGroupIds" },
            "PrivateIpAddress": {
              "Fn::If": [
                "AssignStaticPrivateIp",
                { "Ref": "PrivateIp" },
                { "Ref": "AWS::NoValue" }
              ]
            },
            "SubnetId": { "Ref": "SubnetId" }
          }
        ],
        "Tags": [
          {
            "Key": "Name",
            "Value": {
              "Fn::Join": [
                "",
                [
                  { "Ref": "AWS::StackName" }
                ]
              ]
            }
          }
        ],
        "UserData": {
          "Fn::Base64": {
            "Fn::Join": [
              "",
              [
                "Content-Type: multipart/mixed; boundary=\"===============3585321300151562773==\"\n",
                "MIME-Version: 1.0\n",
                "\n",
                "--===============3585321300151562773==\n",
                "Content-Type: text/cloud-config; charset=\"us-ascii\"\n",
                "MIME-Version: 1.0\n",
                "Content-Transfer-Encoding: 7bit\n",
                "Content-Disposition: attachment; filename=\"cloud.cfg\"\n",
                "\n",
                "#cloud-config\n",
                "\n",
                "system_info:\n",
                "  default_user:\n",
                "    name: ",
                { "Ref": "ProvisionUser" },
                "\n",
                "\n",
                "hostname: ",
                  { "Ref": "WatchmakerComputerName" },
                "\n",
                "\n",
                "growpart:\n",
                "  mode: auto\n",
                "  devices: [ '/dev/xvda', '/dev/xvda2', '/dev/nvme0n1p2' ]\n",
                "  ignore_growroot_disabled: false\n",
                "\n",
                {
                  "Fn::If": [
                    "CreateAppVolume",
                    {
                      "Fn::Join": [
                        "",
                        [
                          "bootcmd:\n",
                          "- cloud-init-per instance appvolume mkfs -t ext4 ",
                          {
                            "Fn::If": [
                              "NotGenFive",
                              {
                                "Fn::FindInMap": [
                                  "InstanceTypeCapabilities",
                                  "PreGenFive",
                                  "InternDeviceName"
                                ]
                              },
                              {
                                "Fn::FindInMap": [
                                  "InstanceTypeCapabilities",
                                  "IsGenFive",
                                  "InternDeviceName"
                                ]
                              }
                            ]
                          },
                          "\n",
                          "mounts:\n",
                          "- [ ",
                          {
                            "Fn::If": [
                              "NotGenFive",
                              {
                                "Fn::FindInMap": [
                                  "InstanceTypeCapabilities",
                                  "PreGenFive",
                                  "InternDeviceName"
                                ]
                              },
                              {
                                "Fn::FindInMap": [
                                  "InstanceTypeCapabilities",
                                  "IsGenFive",
                                  "InternDeviceName"
                                ]
                              }
                            ]
                          },
                          ", ",

                          { "Ref": "AppVolumeMountPath" },
                          " ]\n"
                        ]
                      ]
                    },
                    { "Ref": "AWS::NoValue" }
                  ]
                },
                "\n",
                "--===============3585321300151562773==\n",
                "Content-Type: text/x-shellscript; charset=\"us-ascii\"\n",
                "MIME-Version: 1.0\n",
                "Content-Transfer-Encoding: 7bit\n",
                "Content-Disposition: attachment; filename=\"script.sh\"\n",
                "\n",
                "#!/bin/bash -xe\n\n",
                "\n",
                "# Extend any available LVM PVs\n",
                "if [[ -x $( which pvs ) ]]\n",
                "then\n",
                "   LVMPVS=($(pvs --noheadings -o pv_name))\n",
                "   for PV in \"${LVMPVS[@]}\"\n",
                "   do\n",
                "      pvresize ${PV}\n",
                "   done\n",
                "\n",
                "   vgdisplay -s\n",
                "   VGSFREE=$( vgs --noheadings --units=g --nosuffix -o vg_free | sed -e 's/^ *//' -e  's/\\..*$//' )\n",
                "   ROOTVOL=\"$( awk '/\\s\\/\\s/{ print $1}' /etc/fstab )\"\n",
                "   if [[ ${VGSFREE} -gt 0 ]] && [[ ${VGSFREE} -le 2 ]]\n",
                "   then\n",
                "      echo \"Attempting use free space in VG to expand ${ROOTVOL}\"\n",
                "      lvextend -r -l +100%FREE \"${ROOTVOL}\"\n",
                "   elif [[ ${VGSFREE} -gt 2 ]]\n",
                "   then\n",
                "      echo \"Attempting to expand ${ROOTVOL} by 2GiB\"\n",
                "      lvextend -r -L +2G \"${ROOTVOL}\"\n",
                "   else\n",
                "      echo \"Cannot expand ${ROOTVOL}\"\n",
                "   fi\n",
                "fi\n",
                "\n",
                "# Export AWS ENVs\n",
                "test -r /etc/aws/models/endpoints.json && export AWS_DATA_PATH=/etc/aws/models || true\n",
                "export AWS_CA_BUNDLE=/etc/pki/tls/certs/ca-bundle.crt\n",
                "export REQUESTS_CA_BUNDLE=/etc/pki/tls/certs/ca-bundle.crt\n",
                "export AWS_DEFAULT_REGION=",
                { "Ref": "AWS::Region" },
                "\n\n",
                "# Add local hostname binding\n",
                "printf \"%s\\t%s %s\\n\" ",
                "\"$( ip addr show eth0 | sed -n '/eth0$/p' | sed -e 's/^ *inet *//' -e 's#/.*$##' )\" ",
                "\"$( hostname -f)\" \"$( hostname -s )\" >> /etc/hosts\n",
                "\n",
                {
                  "Fn::If": [
                    "UseWatchmaker",
                    [
                      "# Get pip\n",
                      "PYPI_URL=",
                      { "Ref": "PypiIndexUrl" },
                      "\n",
                      "curl --silent --show-error --retry 5 -L ",
                      { "Ref": "CfnGetPipUrl" },
                      " | python - --index-url=\"$PYPI_URL\" 'wheel<0.30.0;python_version<\"2.7\"' 'wheel;python_version>=\"2.7\"'",
                      "\n\n",
                      "# Add pip to path\n",
                      "hash pip 2> /dev/null || ",
                      "PATH=\"${PATH}:/usr/local/bin\"",
                      "\n\n",
                      "# Upgrade pip and setuptools\n",
                      "pip install",
                      " --index-url=\"$PYPI_URL\"",
                      " --upgrade 'pip<10' 'setuptools<37;python_version<\"2.7\"' 'setuptools;python_version>=\"2.7\"'",
                      "\n\n",
                      "# Fix python urllib3 warnings\n",
                      "yum -y install gcc python-devel libffi-devel openssl-devel\n",
                      "pip install",
                      " --index-url=\"$PYPI_URL\"",
                      " --upgrade 'pycparser<2.19;python_version<\"2.7\"' cffi\n",
                      "pip install",
                      " --index-url=\"$PYPI_URL\"",
                      " --upgrade 'pycparser<2.19;python_version<\"2.7\"' 'cryptography<2.2;python_version<\"2.7\"' 'cryptography;python_version>=\"2.7\"'",
                      "\n\n",
                      "if [[ $(rpm --quiet -q aws-cfn-bootstrap || pip show --quiet aws-cfn-bootstrap)$? -ne 0 ]]\n",
                      "then\n",
                      "  # Get cfn utils\n",
                      "  pip install",
                      " --index-url=\"$PYPI_URL\"",
                      " --upgrade --upgrade-strategy only-if-needed ",
                      { "Ref": "CfnBootstrapUtilsUrl" },
                      "\n\n",
                      "  # Fixup cfn utils\n",
                      "  INITDIR=$(find -L /opt/aws/apitools/cfn-init/init -name redhat",
                      " 2> /dev/null || echo /usr/init/redhat)\n",
                      "  chmod 775 ${INITDIR}/cfn-hup\n",
                      "  ln -f -s ${INITDIR}/cfn-hup /etc/rc.d/init.d/cfn-hup\n",
                      "  chkconfig --add cfn-hup\n",
                      "  chkconfig cfn-hup on\n",
                      "  mkdir -p /opt/aws/bin\n",
                      "  BINDIR=$(find -L /opt/aws/apitools/cfn-init -name bin",
                      " 2> /dev/null || echo /usr/bin)\n",
                      "  for SCRIPT in cfn-elect-cmd-leader cfn-get-metadata cfn-hup",
                      " cfn-init cfn-send-cmd-event cfn-send-cmd-result cfn-signal\n",
                      "  do\n",
                      "  ln -s ${BINDIR}/${SCRIPT} /opt/aws/bin/${SCRIPT} 2> /dev/null || ",
                      "  echo Skipped symbolic link, /opt/aws/bin/${SCRIPT} already exists\n",
                      "  done\n\n",
                      "fi\n\n",
                      "# Remove gcc now that it is no longer needed\n",
                      "yum -y remove gcc --setopt=clean_requirements_on_remove=1\n\n"
                    ],
                    { "Ref": "AWS::NoValue" }
                  ]
                },
                "# Add cfn utils to path\n",
                "hash cfn-signal 2> /dev/null || ",
                "PATH=\"${PATH}:/usr/local/bin:/opt/aws/bin\"",
                "\n\n",
                "# Update cfn-bootstrapper hash method\n",
                "printf 'Updating CFn hash-check method... '\n",
                "PYVERS=$(python -c 'import sys;",
                  " version=sys.version_info[:2];",
                  " print(\"{0}.{1}\".format(*version))')\n",
                "sed -i '/^[ \\t][ \\t]*self._etag/s/etag$/None/'",
                  " /usr/lib/python${PYVERS}/site-packages/cfnbootstrap",
                  "/util.py && echo 'Success' || ",
                  "err_exit 'Failed updating CFn hash-method'\n",
                "\n",
                "# Execute cfn-init\n",
                "cfn-init -v -c launch",
                " --stack ",
                { "Ref": "AWS::StackName" },
                " --resource GitLabMaster",
                {
                  "Fn::If": [
                    "AssignInstanceRole",
                    {
                      "Fn::Join": [
                        "",
                        [
                          " --role ",
                          { "Ref": "InstanceRoleName" }
                        ]
                      ]
                    },
                    ""
                  ]
                },
                {
                  "Fn::If": [
                    "UseCfnUrl",
                    {
                      "Fn::Join": [
                        "",
                        [
                          " --url ",
                          { "Ref": "CfnEndpointUrl" }
                        ]
                      ]
                    },
                    ""
                  ]
                },
                " --region ",
                { "Ref": "AWS::Region" },
                " ||",
                " ( echo 'ERROR: cfn-init failed! Aborting!';",
                " cfn-signal -e 1",
                "  --stack ",
                { "Ref": "AWS::StackName" },
                "  --resource GitLabMaster",
                {
                  "Fn::If": [
                    "AssignInstanceRole",
                    {
                      "Fn::Join": [
                        "",
                        [
                          " --role ",
                          { "Ref": "InstanceRoleName" }
                        ]
                      ]
                    },
                    ""
                  ]
                },
                {
                  "Fn::If": [
                    "UseCfnUrl",
                    {
                      "Fn::Join": [
                        "",
                        [
                          " --url ",
                          { "Ref": "CfnEndpointUrl" }
                        ]
                      ]
                    },
                    ""
                  ]
                },
                "  --region ",
                { "Ref": "AWS::Region" },
                ";",
                " exit 1",
                " )\n\n",
                {
                  "Fn::If": [
                    "AttachToElb",
                    {
                      "Fn::Join": [
                        "",
                        [
                          "# Register to Named ELB\n",
                          "aws elb --region ",
                          { "Ref": "AWS::Region" },
                          " register-instances-with-load-balancer --load-balancer-name ",
                          { "Ref": "ElbName" },
                          " --instances ",
                          " $( curl -skl http://169.254.169.254/latest/meta-data/instance-id/ )",
                          "\n"
                        ]
                      ]
                    },
                    ""
                  ]
                },
                "\n",
                "--===============3585321300151562773==--"
              ]
            ]
          }
        }
      },
      "Type": "AWS::EC2::Instance"
    },
    "GitLabMasterLogGroup": {
      "Condition": "InstallCloudWatchAgent",
      "Properties": {
        "LogGroupName": {
          "Fn::Join": [
            "",
            [
              "/aws/ec2/lx/",
              { "Ref": "AWS::StackName" }
            ]
          ]
        }
      },
      "Type": "AWS::Logs::LogGroup"
    }
  }
}
